scCAPE/__init__.py
scCAPE/dataDL.py
scCAPE/modelDL.py
scCAPE/plotting.py
scCAPE/sccape.py
scCAPE-0.1.0.dist-info/LICENSE.txt
scCAPE-0.1.0.dist-info/METADATA
scCAPE-0.1.0.dist-info/WHEEL
scCAPE-0.1.0.dist-info/top_level.txt
scCAPE-0.1.0.dist-info/RECORD
