Metadata-Version: 2.1
Name: scCAPE
Version: 0.1.0
Summary: Inference of heterogeneous perturbation effects in single cell CRISPR screening data
Author: ZichuFu
Author-email: 1779404540@qq.com
Platform: all
Classifier: Intended Audience :: Developers
Classifier: Operating System :: OS Independent
Classifier: Natural Language :: Chinese (Simplified)
Classifier: Programming Language :: Python
License-File: LICENSE.txt
Requires-Dist: torch
Requires-Dist: scanpy
Requires-Dist: econml
Requires-Dist: scikit-learn
Requires-Dist: scipy
Requires-Dist: scib
Requires-Dist: statsmodels
